telstra/__init__.py
telstra/messaging/__init__.py
telstra/messaging/exceptions.py
telstra/messaging/free_trial_numbers.py
telstra/messaging/health_check.py
telstra/messaging/message.py
telstra/messaging/oauth.py
telstra/messaging/reports.py
telstra/messaging/types.py
telstra/messaging/utils/__init__.py
telstra/messaging/utils/callback_url.py
telstra/messaging/utils/config.py
telstra/messaging/utils/error_response.py
telstra/messaging/utils/free_trial_number.py
telstra/messaging/utils/message_id.py
telstra/messaging/utils/querystring.py
telstra/messaging/utils/reports_dates.py
telstra/messaging/utils/schedule_send.py
telstra/messaging/utils/virtual_number.py
telstra/messaging/virtual_number.py
telstra_messaging-3.3.19.dist-info/LICENSE
telstra_messaging-3.3.19.dist-info/METADATA
telstra_messaging-3.3.19.dist-info/WHEEL
telstra_messaging-3.3.19.dist-info/RECORD
