Metadata-Version: 2.1
Name: telstra.messaging
Version: 3.3.19
Summary: SDK for the Telstra Messaging API V3 - Beta
License: Apache-2.0
Author: David Andersson
Author-email: david-andersson@users.noreply.github.com 
Requires-Python: >=3.10,<4.0
Classifier: License :: OSI Approved :: Apache Software License
Classifier: Programming Language :: Python :: 3
Classifier: Programming Language :: Python :: 3.10
Classifier: Programming Language :: Python :: 3.11
Classifier: Programming Language :: Python :: 3.12
